spikeinterface_gui/__init__.py
spikeinterface_gui/backend_panel.py
spikeinterface_gui/backend_qt.py
spikeinterface_gui/basescatterview.py
spikeinterface_gui/controller.py
spikeinterface_gui/crosscorrelogramview.py
spikeinterface_gui/curation_tools.py
spikeinterface_gui/curationview.py
spikeinterface_gui/isiview.py
spikeinterface_gui/launcher.py
spikeinterface_gui/layout_presets.py
spikeinterface_gui/main.py
spikeinterface_gui/mainsettingsview.py
spikeinterface_gui/mergeview.py
spikeinterface_gui/metricsview.py
spikeinterface_gui/myqt.py
spikeinterface_gui/ndscatterview.py
spikeinterface_gui/probeview.py
spikeinterface_gui/similarityview.py
spikeinterface_gui/spikeamplitudeview.py
spikeinterface_gui/spikedepthview.py
spikeinterface_gui/spikelistview.py
spikeinterface_gui/spikerateview.py
spikeinterface_gui/tracemapview.py
spikeinterface_gui/traceview.py
spikeinterface_gui/unitlistview.py
spikeinterface_gui/utils_global.py
spikeinterface_gui/utils_panel.py
spikeinterface_gui/utils_qt.py
spikeinterface_gui/version.py
spikeinterface_gui/view_base.py
spikeinterface_gui/viewlist.py
spikeinterface_gui/waveformheatmapview.py
spikeinterface_gui/waveformview.py
spikeinterface_gui/img/si.png
spikeinterface_gui-0.12.0.dist-info/licenses/LICENSE
spikeinterface_gui-0.12.0.dist-info/METADATA
spikeinterface_gui-0.12.0.dist-info/WHEEL
spikeinterface_gui-0.12.0.dist-info/entry_points.txt
spikeinterface_gui-0.12.0.dist-info/top_level.txt
spikeinterface_gui-0.12.0.dist-info/RECORD
