Metadata-Version: 2.4
Name: spikeinterface-gui
Version: 0.12.0
Summary: Qt GUI for spikeinterface
Author-email: Samuel Garcia <sam.garcia.die@gmail.com>, Alessio Buccino <alessiop.buccino@gmail.com>
Project-URL: Homepage, https://github.com/SpikeInterface/spikeinterface-gui
Project-URL: Repository, https://github.com/SpikeInterface/spikeinterface-gui
Classifier: Programming Language :: Python :: 3
Classifier: License :: OSI Approved :: MIT License
Classifier: Operating System :: OS Independent
Requires-Python: >=3.10
License-File: LICENSE
Requires-Dist: spikeinterface[full]>=0.103.0
Requires-Dist: markdown
Provides-Extra: desktop
Requires-Dist: PySide6==6.7.3; extra == "desktop"
Requires-Dist: pyqtgraph; extra == "desktop"
Provides-Extra: web
Requires-Dist: panel; extra == "web"
Requires-Dist: bokeh; extra == "web"
Provides-Extra: test
Requires-Dist: pytest; extra == "test"
Requires-Dist: PySide6==6.7.3; extra == "test"
Provides-Extra: docs
Requires-Dist: sphinx>=5.0; extra == "docs"
Requires-Dist: sphinx_rtd_theme; extra == "docs"
Dynamic: license-file
